simplevent/__init__.py
simplevent-2.2.0.dist-info/LICENSE.txt
simplevent-2.2.0.dist-info/METADATA
simplevent-2.2.0.dist-info/WHEEL
simplevent-2.2.0.dist-info/top_level.txt
simplevent-2.2.0.dist-info/RECORD
