Metadata-Version: 2.2
Name: simplevent
Version: 2.2.0
Summary: A simple framework for event-driven programming, based on the Observer design pattern.
Home-page: https://github.com/matheusvilano/simplevent.git
Author: Matheus Vilano
Author-email: 
License: MIT
Project-URL: Author Website, https://www.matheusvilano.com/
Project-URL: Git Repository, https://github.com/matheusvilano/simplevent
Keywords: event observer listener subscription subscriber subject design pattern callback
Classifier: Development Status :: 5 - Production/Stable
Classifier: Intended Audience :: Developers
Classifier: License :: OSI Approved :: MIT License
Classifier: Operating System :: OS Independent
Classifier: Programming Language :: Python :: 3
Requires-Python: >=3.11
License-File: LICENSE.txt
Dynamic: author
Dynamic: classifier
Dynamic: description
Dynamic: description-content-type
Dynamic: home-page
Dynamic: keywords
Dynamic: license
Dynamic: project-url
Dynamic: requires-python
Dynamic: summary
